ci_cd_secrets/__init__.py
ci_cd_secrets/main.py
ci_secrets/__init__.py
ci_secrets/main.py
ci_cd_secrets-1.0.1.dist-info/LICENSE.md
ci_cd_secrets-1.0.1.dist-info/METADATA
ci_cd_secrets-1.0.1.dist-info/WHEEL
ci_cd_secrets-1.0.1.dist-info/entry_points.txt
ci_cd_secrets-1.0.1.dist-info/top_level.txt
ci_cd_secrets-1.0.1.dist-info/RECORD
